odoo/addons/fieldservice_base_location/README.rst
odoo/addons/fieldservice_base_location/__init__.py
odoo/addons/fieldservice_base_location/__manifest__.py
odoo/addons/fieldservice_base_location/i18n/ca.po
odoo/addons/fieldservice_base_location/i18n/es.po
odoo/addons/fieldservice_base_location/i18n/fieldservice_base_location.pot
odoo/addons/fieldservice_base_location/i18n/it.po
odoo/addons/fieldservice_base_location/models/__init__.py
odoo/addons/fieldservice_base_location/models/fsm_location.py
odoo/addons/fieldservice_base_location/readme/CONTRIBUTORS.md
odoo/addons/fieldservice_base_location/readme/DESCRIPTION.md
odoo/addons/fieldservice_base_location/readme/USAGE.md
odoo/addons/fieldservice_base_location/static/description/icon.png
odoo/addons/fieldservice_base_location/static/description/index.html
odoo/addons/fieldservice_base_location/tests/__init__.py
odoo/addons/fieldservice_base_location/tests/test_address_autocomplete.py
odoo/addons/fieldservice_base_location/views/fsm_location.xml
odoo_addon_fieldservice_base_location-17.0.1.0.0.4.dist-info/METADATA
odoo_addon_fieldservice_base_location-17.0.1.0.0.4.dist-info/WHEEL
odoo_addon_fieldservice_base_location-17.0.1.0.0.4.dist-info/top_level.txt
odoo_addon_fieldservice_base_location-17.0.1.0.0.4.dist-info/RECORD
