Metadata-Version: 2.1
Name: odoo-addon-fieldservice_base_location
Version: 17.0.1.0.0.4
Requires-Python: >=3.10
Requires-Dist: odoo-addon-base_location>=17.0dev,<17.1dev
Requires-Dist: odoo-addon-fieldservice>=17.0dev,<17.1dev
Requires-Dist: odoo>=17.0a,<17.1dev
Summary: Autocomplete address in field service locations
Home-page: https://github.com/OCA/field-service
License: AGPL-3
Author: Apsl - Nagarro, Odoo Community Association (OCA)
Author-email: support@odoo-community.org
Classifier: Programming Language :: Python
Classifier: Framework :: Odoo
Classifier: Framework :: Odoo :: 17.0
Classifier: License :: OSI Approved :: GNU Affero General Public License v3
